{
    "title": "Best AI Stocks In India - Artificial Intelligence Stocks",
    "headings": {
        "h1": [
            "Best AI Stocks In India – Artificial Intelligence Stocks"
        ],
        "h2": [
            "Introduction to Best AI Stocks",
            "What Are AI Stocks In India?",
            "Features Of Artificial Stocks In India",
            "Artificial Intelligence Stocks Based on 6-Month Return",
            "Top AI Stocks In India Based on 5-Year Net Profit Margin",
            "Best AI Stocks In India For Long Term Based on 1M Return",
            "High Dividend Yield AI Stocks",
            "Historical Performance of AI Stock In India",
            "Factors To Consider When Investing In AI Stock In India",
            "How To Invest In Top AI Stocks?",
            "Impact of Government Policies on Top AI Stocks In India",
            "How AI Stocks In India Perform in Economic Downturns?",
            "Advantages Of Investing In Artificial Intelligence Stocks In India?",
            "Risks Of Investing In AI Stocks?",
            "AI Stocks In India’s GDP Contribution",
            "Who Should Invest In Best AI Stocks In India?",
            "Top Artificial Intelligence Companies In India Listed On NSE FAQs"
        ],
        "h3": [
            "Tata Consultancy Services Ltd",
            "Infosys Ltd",
            "HCL Technologies Ltd",
            "Wipro Ltd",
            "Tech Mahindra Ltd",
            "Persistent Systems Ltd",
            "Bosch Ltd",
            "Oracle Financial Services Software Ltd",
            "Tata Elxsi Ltd",
            "Affle (India) Ltd",
            "",
            "Top NBFC Stocks In India by Market Capitalisation",
            "Top Cement Stocks In India by Market Capitalisation",
            "Top Cable Stocks In India by Market Capitalisation"
        ]
    },
    "paragraphs": [
        "Home -- Finance -- Best AI Stocks In India – Artificial Intelligence Stocks",
        "1 min read",
        "AI stocks in India refer to shares of companies involved in developing or utilizing artificial intelligence technologies. These companies operate in sectors like technology, automation, healthcare and finance, leveraging AI for innovation and efficiency. Investing in AI stocks provides exposure to India’s growing tech and digital transformation landscape.",
        "The table below shows the best AI stocks in India based on the highest market capitalisation and 1-year return.",
        "The Market Cap of Tata Consultancy Services Ltd is Rs. 13,07,052.21 crores. The stock’s monthly return is -14.07%. Its one-year return is -14.40%. The stock is 1.04% away from its 52-week high."
    ],
    "links": {
        "Stocks": "https://aliceblueonline.com/share-price/",
        "Stock Market News": "https://aliceblueonline.com/stock-market-news/",
        "Trending": "https://aliceblueonline.com/web-stories/trending/",
        "IPO GMP": "https://aliceblueonline.com/stock-market-news/ipo-gmp/",
        "IPO Subscription": "https://aliceblueonline.com/stock-market-news/ipo-subscription/",
        "IPO Allotment": "https://aliceblueonline.com/stock-market-news/ipo-allotment/",
        "Commodities": "https://aliceblueonline.com/stock-market-news/commodities/",
        "Web Stories": "https://aliceblueonline.com/web-stories/",
        "IPO": "https://mutualfunds.aliceblueonline.com/explore/ipo",
        "Market Insight": "https://aliceblueonline.com/web-stories/market-insight/",
        "Personal Finance": "https://aliceblueonline.com/web-stories/personal-finance/",
        "Community": "https://community.aliceblueonline.com/",
        "Contact Us": "https://aliceblueonline.com/contact-us/",
        "Call & Trade": "https://aliceblueonline.com/call-trade/",
        "Blog": "#",
        "Ant IQ": "https://aliceblueonline.com/antiq/",
        "IPO Reviews": "https://aliceblueonline.com/ipo/",
        "Support": "https://aliceblueonline.com/support/",
        "Careers": "https://aliceblueonline.com/careers/",
        "About Us": "https://aliceblueonline.com/about-us/",
        "Products": "https://aliceblueonline.com/products/",
        "ANT Mobi": "https://aliceblueonline.com/ant-mobi/",
        "ANT Web": "https://aliceblueonline.com/ant-web/",
        "ANT Plus": "https://aliceblueonline.com/ant-plus/",
        "1lyoption": "/1lyoption/",
        "TradingView": "https://aliceblueonline.com/tradingview/",
        "Mutual Funds": "https://aliceblueonline.com/mf/",
        "Investments": "https://aliceblueonline.com/investments/",
        "Trade School": "https://tradeschool.aliceblueonline.com/",
        "Advisory": "https://aliceblueonline.com/inuvest/",
        "Pricing": "https://aliceblueonline.com/pricing/",
        "Tools": "#",
        "Pivot Points": "https://aliceblueonline.com/pivot-points/",
        "Brokerage Calculator": "https://aliceblueonline.com/brokerage-calculator/",
        "Margin Calculator": "/margin-calculator/",
        "Trade Finder": "https://aliceblueonline.com/margin-calculator/trade-finder/",
        "Economic Calendar": "https://aliceblueonline.com/economic-calendar/",
        "Pledge & MTF List": "https://bit.ly/3RYk3jh",
        "Partner with Us": "https://aliceblueonline.com/business-partner/",
        "Open Account": "https://aliceblueonline.com/open-account-fill-kyc-request-call-back/?C=WEBEKYC",
        "Login": "#",
        "ANT Web Trading Platform": "https://ant.aliceblueonline.com/",
        "Backoffice (BOT)": "https://bot.aliceblueonline.com/",
        "Partner Dashboard": "https://partners.aliceblueonline.com/",
        "1lyoptions": "https://aliceblueonline.com/1lyoptions/",
        "Important Links": "#",
        "Call Trade": "https://aliceblueonline.com/call-trade/",
        "Refer Us": "https://aliceblueonline.com/refer-us/",
        "ANT IQ": "https://aliceblueonline.com/antiq/",
        "Stories": "https://aliceblueonline.com/web-stories/",
        "Contact us": "https://aliceblueonline.com/contact-us/",
        "Open An Account": "https://aliceblueonline.com/open-account-fill-kyc-request-call-back/",
        "Whatsapp": "https://bit.ly/3OtWQUu",
        "Envelope": "#",
        "Facebook": "https://www.facebook.com/aliceblue.commodities",
        "Linkedin": "https://www.linkedin.com/company/alice-blue-commodities-p-ltd",
        "Home": "https://aliceblueonline.com/",
        "Finance": "https://aliceblueonline.com/f/",
        "Alice Blue": "https://aliceblueonline.com/open-account-fill-kyc-request-call-back/?C=WEBEKYC",
        "Shares below 10": "https://aliceblueonline.com/antiq/opportunity/shares-below-10-rupees/",
        "Best Dividend Yield Fund": "https://aliceblueonline.com/best-dividend-yield-fund/",
        "Shares below 100": "https://aliceblueonline.com/antiq/opportunity/shares-below-100-rupees",
        "Best Large And Mid Cap Mutual Funds": "https://aliceblueonline.com/best-large-and-midcap-fund/",
        "Large Cap Stocks": "https://aliceblueonline.com/antiq/opportunity/best-large-cap-stocks-in-india/",
        "High-beta Stocks": "https://aliceblueonline.com/high-beta-stocks/",
        "Best Blue Chip Stocks in India": "https://aliceblueonline.com/antiq/opportunity/best-blue-chip-stocks-in-india/",
        "Best Shares Below 500 Rupees": "https://aliceblueonline.com/stocks-under-500/",
        "Education Stocks in India": "https://aliceblueonline.com/top-education-stocks-in-india/",
        "Otm In Mutual Fund": "https://aliceblueonline.com/otm-full-form/",
        "Leather stocks india": "https://aliceblueonline.com/best-leather-stocks-in-india/",
        "Advantages Of Secondary Market": "https://aliceblueonline.com/advantages-of-secondary-market/#:~:text=The%20primary%20advantage%20of%20the,it%20even%20easier%20for%20investors.",
        "Most Volatile Stocks": "https://aliceblueonline.com/most-volatile-stocks/",
        "CNC vs MIS": "https://aliceblueonline.com/antiq/o/cnc-vs-mis-order/",
        "Nifty 50 Companies": "https://aliceblueonline.com/antiq/opportunity/nifty-50-companies-list/",
        "BTST Trading": "https://aliceblueonline.com/antiq/beginner/what-is-btst-trading/",
        "Electronic stocks": "https://aliceblueonline.com/electronic-stocks/",
        "What is a Sub Broker?": "https://aliceblueonline.com/hindi/sub-broker-meaning-in-hindi/",
        "Best Flexi Cap Mutual Funds": "https://aliceblueonline.com/best-flexi-cap-mutual-funds/",
        "What is Sensex?": "https://aliceblueonline.com/antiq/organization/sensex-meaning/",
        "Vinayak Hagargi": "https://aliceblueonline.com/author/vinayak-hagargi/",
        "More About The Author": "https://aliceblueonline.com/author/vinayak-hagargi/",
        "Partnership": "https://aliceblueonline.com/antiq/partnership/",
        "Organization": "https://aliceblueonline.com/antiq/organization/",
        "Order Types": "https://aliceblueonline.com/antiq/order-types/",
        "Opportunity": "https://aliceblueonline.com/antiq/opportunity/",
        "Hindi": "https://aliceblueonline.com/hindi/",
        "Commodity": "https://aliceblueonline.com/antiq/commodity/",
        "Tamil": "https://aliceblueonline.com/tamil/",
        "Kannada": "https://aliceblueonline.com/kannada/",
        "Top NBFC Stocks In India by Market Capitalisation": "https://aliceblueonline.com/top-nbfc-stocks-in-india-by-market-capitalisation/",
        "Top Cement Stocks In India by Market Capitalisation": "https://aliceblueonline.com/top-cement-stocks-in-india-by-market-capitalisation/",
        "Top Cable Stocks In India by Market Capitalisation": "https://aliceblueonline.com/top-cable-stocks-in-india-by-market-capitalisation/",
        "Best Beverage Stocks in India – Beverage Stocks": "https://aliceblueonline.com/best-beverage-stocks-in-india/",
        "Stocks Under 20 Rs – Best Stocks Under 20": "https://aliceblueonline.com/antiq/opportunity/shares-below-20-rupees/",
        "Best Stocks Under 50 – Stocks Under 50": "https://aliceblueonline.com/antiq/opportunity/shares-below-50-rupees/",
        "Monopoly Stocks – Best Monopoly Stocks in India 2025": "https://aliceblueonline.com/antiq/opportunity/monopoly-stocks/",
        "Best Shares Below 1 Rupee": "https://aliceblueonline.com/antiq/opportunity/shares-below-1-rupee/",
        "Best Low Price Shares To Buy in 2025": "https://aliceblueonline.com/best-low-price-shares-to-buy/",
        "Best Share Under 5 Rs – Stocks Under 5 Rs": "https://aliceblueonline.com/antiq/opportunity/shares-below-5-rupees/",
        "Penny Stock List – Best Penny Stocks To Buy In India 2025": "https://aliceblueonline.com/antiq/opportunity/penny-stock-list/",
        "Most Expensive Share in India": "https://aliceblueonline.com/antiq/opportunity/most-expensive-shares-in-india/",
        "Difference Between Annual Return And Absolute Return": "https://aliceblueonline.com/annual-return-vs-absolute-return/",
        "Advantages and Disadvantages of Mutual Funds": "https://aliceblueonline.com/advantages-and-disadvantages-of-mutual-funds/",
        "Tourism Stocks In India – Tourism Stocks": "https://aliceblueonline.com/tourism-stocks-india/",
        "Floating Rate Bonds: Meaning, Types and Advantages": "https://aliceblueonline.com/floating-rate-bonds/",
        "Difference Between Open Ended And Close Ended Mutual Fund": "https://aliceblueonline.com/difference-between-open-ended-and-close-ended-mutual-fund/",
        "Best Balanced Advantage Funds – Balanced Advantage Funds": "https://aliceblueonline.com/balanced-advantage-funds/",
        "Mutual Fund Redemption": "https://aliceblueonline.com/mutual-fund-redemption/",
        "What Is Earnings Per Share?": "https://aliceblueonline.com/what-is-earnings-per-share/",
        "ELSS Mutual Funds – Best Performing ELSS Mutual Funds": "https://aliceblueonline.com/best-elss-mutual-fund/",
        "What Is A Debt Mutual Fund?": "https://aliceblueonline.com/what-is-debt-mutual-fund/",
        "Exchange Traded Funds India": "https://aliceblueonline.com/antiq/beginner/what-is-an-etf/",
        "Difference Between FDI and FII – Do They Help in a Country’s Economic Growth?": "https://aliceblueonline.com/antiq/beginner/difference-between-fdi-and-fii/",
        "Downloads": "/downloads/",
        "Circulars": "/circulars/",
        "Bank Details": "/bank-details/",
        "How to Videos": "/how-to-videos/",
        "Instagram": "https://www.instagram.com/aliceblue_financialservices/",
        "Telegram": "https://t.me/Alicebluelive",
        "Youtube": "https://www.youtube.com/channel/UCrAM1_NV3j5_l8VoukiXv2g?sub_confirmation=1",
        "AB Cares": "https://aliceblueonline.com/cares/",
        "HRMS Login": "https://hrms.aliceblueonline.com/",
        "EKYC Guidelines": "https://aliceblueonline.com/ekyc-guidelines/",
        "ANT API": "https://aliceblueonline.com/ant-plus/",
        "Rise (MF, G-Sec, T-Bills)": "https://mutualfunds.aliceblueonline.com/",
        "RMS Live Updates": "https://aliceblueonline.com/rms-live-updates/exposures/",
        "KYC Tracker": "https://app.aliceblueonline.com/digilink/LeadTracker.aspx",
        "Trading Holidays": "https://aliceblueonline.com/trading-holidays-2025/",
        "PR Coverage": "https://aliceblueonline.com/media-coverage/",
        "Employee Referral Policy": "https://aliceblueonline.com/employee-referral-program/",
        "NSE": "https://www.nseindia.com/",
        "BSE": "https://www.bseindia.com/",
        "MCX": "https://www.mcxindia.com/",
        "MCX-SX": "https://www.msei.in/Index",
        "CDSL": "https://www.cdslindia.com/index.html",
        "SEBI": "https://www.sebi.gov.in/",
        "SCORES portal": "https://scores.gov.in/scores/Welcome.html",
        "SEBI SCORES 2.0": "https://scores.sebi.gov.in/",
        "ODR platform": "https://smartodr.in/login/",
        "accountactivation@aliceblueindia.com": "mailto:accountactivation@aliceblueindia.com",
        "funds@aliceblueindia.com": "mailto:funds@aliceblueindia.com",
        "Bank Details.": "https://alicebluewebsite.s3.ap-south-1.amazonaws.com/wp-content/uploads/2024/04/16043642/USNCBA.pdf",
        "DND Policy": "/legal-documentation/policy-for-dnd-ndnc/",
        "Investor Charter": "/investor-charter/",
        "Legal Documentation": "/legal-documentation/",
        "Privacy Policy": "/legal-documentation/privacy-policy/",
        "Feedback": "/feedback/",
        "Annual Returns": "/annual-returns/",
        "Advisory for Investors": "/legal-documentation/advisory-for-investors/",
        "E-voting": "https://evoting.cdslindia.com/Evoting/EvotingLogin",
        "Mandatory Member Details": "/mandatory-member-details/",
        "Open Free Demat Account": "https://aliceblueonline.com/open-account-fill-kyc-request-call-back/?C=mobilecta"
    }
}